chickenpy/__init__.py
chickenpy/__main__.py
chickenpy/compiler.py
chickenpy/vm.py
chickenpy-0.1.0.dist-info/entry_points.txt
chickenpy-0.1.0.dist-info/LICENSE
chickenpy-0.1.0.dist-info/WHEEL
chickenpy-0.1.0.dist-info/METADATA
chickenpy-0.1.0.dist-info/RECORD
